LICENSE
README.md
setup.py
spark_submit/__info__.py
spark_submit/__init__.py
spark_submit/_defaults.py
spark_submit/exceptions.py
spark_submit/sparkjob.py
spark_submit/system.py
spark_submit.egg-info/PKG-INFO
spark_submit.egg-info/SOURCES.txt
spark_submit.egg-info/dependency_links.txt
spark_submit.egg-info/requires.txt
spark_submit.egg-info/top_level.txt
spark_submit.egg-info/zip-safe
tests/__init__.py
tests/run_integration_test.py
tests/test_sparkjob.py
tests/test_system.py