Metadata-Version: 2.1
Name: spark-submit
Version: 1.4.0
Summary: Python manager for spark-submit jobs
Home-page: https://github.com/PApostol/spark-submit
Author: PApostol
Author-email: foo@bar.com
Maintainer: PApostol
License: MIT
Keywords: apache,spark,submit
Platform: any
Classifier: Development Status :: 4 - Beta
Classifier: Intended Audience :: Developers
Classifier: License :: OSI Approved :: MIT License
Classifier: Topic :: Software Development :: Libraries
Classifier: Topic :: Utilities
Classifier: Programming Language :: Python :: 3.7
Classifier: Programming Language :: Python :: 3.8
Classifier: Programming Language :: Python :: 3.9
Classifier: Programming Language :: Python :: 3.10
Classifier: Programming Language :: Python :: 3.11
Classifier: Programming Language :: Python :: Implementation :: CPython
Classifier: Operating System :: OS Independent
Requires-Python: ~=3.7
License-File: LICENSE
